dc_conversations/__init__.py
dc_conversations/agents/__init__.py
dc_conversations/agents/agent_router.py
dc_conversations/agents/conversation_agents.py
dc_conversations/agents/pydantic_ai_utils.py
dc_conversations/conversation_models.py
dc_conversations/conversations_classes.py
dc_conversations/conversations_router.py
dc_conversations/groq_utils.py
dc_conversations/open_router.py
dataclouder_conversation_ai_cards-0.0.9.dist-info/METADATA
dataclouder_conversation_ai_cards-0.0.9.dist-info/WHEEL
dataclouder_conversation_ai_cards-0.0.9.dist-info/RECORD
