Metadata-Version: 2.3
Name: dataclouder-conversation-ai-cards
Version: 0.0.9
Summary: A library for managing AI conversations and character cards
Author: adamo figueroa
Author-email: adamo@dataclouder.com
Requires-Python: >=3.11
Classifier: Programming Language :: Python :: 3
Classifier: Programming Language :: Python :: 3.11
Classifier: Programming Language :: Python :: 3.12
Classifier: Programming Language :: Python :: 3.13
Requires-Dist: dataclouder-core (>=0.0.1)
Requires-Dist: fastapi (>=0.100.0)
Requires-Dist: pydantic-ai (>=0.0.19)
